odoo/addons/mrp_production_allow_recursive/README.rst
odoo/addons/mrp_production_allow_recursive/__init__.py
odoo/addons/mrp_production_allow_recursive/__manifest__.py
odoo/addons/mrp_production_allow_recursive/i18n/it.po
odoo/addons/mrp_production_allow_recursive/i18n/mrp_production_allow_recursive.pot
odoo/addons/mrp_production_allow_recursive/models/__init__.py
odoo/addons/mrp_production_allow_recursive/models/mrp_production.py
odoo/addons/mrp_production_allow_recursive/models/res_company.py
odoo/addons/mrp_production_allow_recursive/models/res_config_settings.py
odoo/addons/mrp_production_allow_recursive/readme/CONFIGURE.md
odoo/addons/mrp_production_allow_recursive/readme/CONTEXT.md
odoo/addons/mrp_production_allow_recursive/readme/CONTRIBUTORS.md
odoo/addons/mrp_production_allow_recursive/readme/DESCRIPTION.md
odoo/addons/mrp_production_allow_recursive/static/description/icon.png
odoo/addons/mrp_production_allow_recursive/static/description/index.html
odoo/addons/mrp_production_allow_recursive/tests/__init__.py
odoo/addons/mrp_production_allow_recursive/tests/test_mrp_production_allow_recursive.py
odoo/addons/mrp_production_allow_recursive/views/res_config_settings_views.xml
odoo_addon_mrp_production_allow_recursive-16.0.1.0.0.4.dist-info/METADATA
odoo_addon_mrp_production_allow_recursive-16.0.1.0.0.4.dist-info/WHEEL
odoo_addon_mrp_production_allow_recursive-16.0.1.0.0.4.dist-info/top_level.txt
odoo_addon_mrp_production_allow_recursive-16.0.1.0.0.4.dist-info/RECORD
